MANIFEST.in
README.rst
requirements.txt
setup.cfg
setup.py
sequana_laa.egg-info/PKG-INFO
sequana_laa.egg-info/SOURCES.txt
sequana_laa.egg-info/dependency_links.txt
sequana_laa.egg-info/entry_points.txt
sequana_laa.egg-info/not-zip-safe
sequana_laa.egg-info/requires.txt
sequana_laa.egg-info/top_level.txt
sequana_pipelines/laa/__init__.py
sequana_pipelines/laa/config.yaml
sequana_pipelines/laa/dag.png
sequana_pipelines/laa/laa.rules
sequana_pipelines/laa/main.py
sequana_pipelines/laa/multiqc_config.yaml
sequana_pipelines/laa/requirements.txt
sequana_pipelines/laa/schema.yaml